{
  "data": [
    {
      "id": "UbhgAjZIuLauV1dw2G4QsocHIk83",
      "displayName": "Georgia Jim",
      "own": 234,
      "picked": 256,
      "recorded": 241,
      "wishlist": 0
    },
    {
      "id": "hnX373zhNoT1QZ3lc8IWVEvcz0R2",
      "displayName": "DoctorHogmaster",
      "own": 202,
      "picked": 223,
      "recorded": 172,
      "wishlist": 2
    },
    {
      "id": "8ZAMkphV1WS23gaAcC1UEjuzilf1",
      "displayName": "Dra9i",
      "own": 175,
      "picked": 192,
      "recorded": 135,
      "wishlist": 0
    },
    {
      "id": "f2yySWbxUBXF8k3HgorYhrm76gx2",
      "displayName": "Rein",
      "own": 98,
      "picked": 180,
      "recorded": 158,
      "wishlist": 0
    },
    {
      "id": "JVXjrWEVRgS2ARwOVCHuFdEi3II2",
      "own": 153,
      "picked": 55,
      "recorded": 0,
      "wishlist": 0
    },
    {
      "id": "RQaTIKv1oaWZsJtnJgGkQdQPqDv2",
      "own": 142,
      "picked": 120,
      "recorded": 39,
      "wishlist": 73
    },
    {
      "id": "mZyfQIARjCP1uJJJc7ioMAALV9v2",
      "displayName": "Peace",
      "own": 139,
      "picked": 77,
      "recorded": 47,
      "wishlist": 33
    },
    {
      "id": "NdkmYGydSHfPTcj5xuqjwSyJJI42",
      "displayName": "Greenish",
      "own": 66,
      "picked": 118,
      "recorded": 90,
      "wishlist": 0
    },
    {
      "id": "IzvfeUBxzWcd8VXKHq0T4MUhtQu1",
      "own": 132,
      "picked": 76,
      "recorded": 19,
      "wishlist": 0
    },
    {
      "id": "U3wCYsdGwYS8ujsO2K78iD68FMC3",
      "displayName": "Dig",
      "own": 118,
      "picked": 42,
      "recorded": 7,
      "wishlist": 9
    },
    {
      "id": "XoUDXU5McjTuVnPA1xfmzytcKuy2",
      "displayName": "Red Wanderer",
      "own": 0,
      "picked": 112,
      "recorded": 83,
      "wishlist": 0
    },
    {
      "id": "gWoqbd0FOsglFD5boH96NAtJ7DE3",
      "own": 87,
      "picked": 95,
      "recorded": 84,
      "wishlist": 1
    },
    {
      "id": "yLbxfRWSKyWMZm9r2i2gD19J3Hb2",
      "displayName": "septclues",
      "own": 104,
      "picked": 37,
      "recorded": 10,
      "wishlist": 0
    },
    {
      "id": "AiS1jGKvjhVb4vOhmzVFzx2VNko2",
      "displayName": "FloridaManPicks",
      "own": 101,
      "picked": 69,
      "recorded": 43,
      "wishlist": 17
    },
    {
      "id": "qXhqtUdEVFfrajxqblKl8bqQqXM2",
      "displayName": "DQ",
      "own": 37,
      "picked": 84,
      "recorded": 81,
      "wishlist": 7
    },
    {
      "id": "ohnGCeCEgIOk9KzmxWcsWmGM0nM2",
      "displayName": "7woz3ro51x",
      "own": 28,
      "picked": 71,
      "recorded": 71,
      "wishlist": 0
    },
    {
      "id": "SODQHdFQUPYNqL37yiE2wGgVZUy2",
      "displayName": "takendarkk",
      "own": 81,
      "picked": 42,
      "recorded": 8,
      "wishlist": 21
    },
    {
      "id": "GGplAdctTfVDLVvYsfIADJmfp8f2",
      "displayName": "mgsecure",
      "own": 77,
      "picked": 52,
      "recorded": 13,
      "wishlist": 9
    },
    {
      "id": "FGhShmNkxTXC9vwmZwWylOvU8K72",
      "own": 67,
      "picked": 61,
      "recorded": 21,
      "wishlist": 0
    },
    {
      "id": "mHlFwfstvgSgzUHnBNdKjPVFFgW2",
      "displayName": "McBane",
      "own": 76,
      "picked": 39,
      "recorded": 10,
      "wishlist": 15
    },
    {
      "id": "XKPQaAR525XV2JsqGn12eEKwxD62",
      "own": 62,
      "picked": 49,
      "recorded": 47,
      "wishlist": 17
    },
    {
      "id": "GHJ9pVE1TRTc26VMkcZGbIGaQn82",
      "own": 73,
      "picked": 59,
      "recorded": 2,
      "wishlist": 0
    },
    {
      "id": "e34lNNt1E9Qo5gyiALfqzTuTbNH3",
      "own": 70,
      "picked": 37,
      "recorded": 12,
      "wishlist": 1
    },
    {
      "id": "m70lMclrN7U0oMNeWleMSeyVm5E2",
      "displayName": "fabianoh130",
      "own": 68,
      "picked": 39,
      "recorded": 0,
      "wishlist": 4
    },
    {
      "id": "alxa2VFxUFRzLL4Z6stTm2B8h753",
      "own": 63,
      "picked": 50,
      "recorded": 29,
      "wishlist": 0
    },
    {
      "id": "f206EWl1tZN6wUYoT3r9oaKE6qM2",
      "own": 55,
      "picked": 34,
      "recorded": 9,
      "wishlist": 18
    },
    {
      "id": "xeJIm65Yoxf00D3si9aRaDBCIOJ3",
      "own": 63,
      "picked": 2,
      "recorded": 2,
      "wishlist": 7
    },
    {
      "id": "WMSvvuutyShfvBBYB3PmDe4fmeS2",
      "displayName": "NiXXeD",
      "own": 61,
      "picked": 41,
      "recorded": 36,
      "wishlist": 7
    },
    {
      "id": "KlxbgmsyK5f4r9tQcVmmFhGmbfN2",
      "own": 58,
      "picked": 51,
      "recorded": 33,
      "wishlist": 3
    },
    {
      "id": "BKvVG1FuIyfD1xGYXizjvcnxANu1",
      "own": 57,
      "picked": 35,
      "recorded": 20,
      "wishlist": 4
    },
    {
      "id": "ibBqRqmtuaN40Bumc1A6x6KvSUW2",
      "own": 57,
      "picked": 27,
      "recorded": 0,
      "wishlist": 0
    },
    {
      "id": "q557m7oAjIMdbXzeFTYtxzublEe2",
      "own": 57,
      "picked": 45,
      "recorded": 0,
      "wishlist": 0
    },
    {
      "id": "ydmRY2wuIQWpFeX61US8x6cfWdV2",
      "own": 56,
      "picked": 6,
      "recorded": 0,
      "wishlist": 0
    },
    {
      "id": "NLcgikW1rdZInUwaQUY9WfZRRnq2",
      "own": 51,
      "picked": 10,
      "recorded": 9,
      "wishlist": 0
    },
    {
      "id": "tbaq0CWuDTXerA0eUi0kGASVb1Z2",
      "own": 46,
      "picked": 25,
      "recorded": 9,
      "wishlist": 7
    },
    {
      "id": "KxL1uCNyBeUBBEXTCuBKpK76t462",
      "own": 47,
      "picked": 31,
      "recorded": 4,
      "wishlist": 61
    },
    {
      "id": "myt3S0lXqCdT7gIJg1pckysIpSs2",
      "own": 48,
      "picked": 13,
      "recorded": 11,
      "wishlist": 0
    },
    {
      "id": "bSkotjOGENXHGd3rpo8G3TJeCk33",
      "own": 40,
      "picked": 37,
      "recorded": 27,
      "wishlist": 0
    },
    {
      "id": "caXiJRAD9iaAuR2YWKuUrlPlsb83",
      "own": 46,
      "picked": 20,
      "recorded": 4,
      "wishlist": 0
    },
    {
      "id": "3UX1c0xnWCYEIWyUMfA0ekt4PqC2",
      "own": 43,
      "picked": 16,
      "recorded": 3,
      "wishlist": 8
    },
    {
      "id": "yBn09b92sJY9G7x1tjDIZEDBsiH3",
      "displayName": "thegamingbug",
      "own": 40,
      "picked": 15,
      "recorded": 6,
      "wishlist": 74
    },
    {
      "id": "x28e7HXThnhWvPbzNkyb4kuz7e02",
      "own": 39,
      "picked": 29,
      "recorded": 20,
      "wishlist": 0
    },
    {
      "id": "xZ7Ta6611Yekrql0KD6l0lhoZJ73",
      "own": 36,
      "picked": 33,
      "recorded": 0,
      "wishlist": 2
    },
    {
      "id": "DUhgE7qbw7WwHH7KzJXZblRVFKS2",
      "own": 23,
      "picked": 14,
      "recorded": 0,
      "wishlist": 0
    },
    {
      "id": "nwjZFaTvhcROv9oP0tqorI5o9x02",
      "own": 37,
      "picked": 33,
      "recorded": 9,
      "wishlist": 0
    },
    {
      "id": "XX8BzLAvqmPeBTiqcdPZzojsTPF2",
      "displayName": "tonysansan",
      "own": 37,
      "picked": 32,
      "recorded": 31,
      "wishlist": 0
    },
    {
      "id": "V7Hb0ChoMkQDN5VSokfFBU9d5Zp1",
      "own": 36,
      "picked": 23,
      "recorded": 4,
      "wishlist": 0
    },
    {
      "id": "q4MiwCXoRiWGXU408BXARkbvEEW2",
      "own": 34,
      "picked": 31,
      "recorded": 0,
      "wishlist": 0
    },
    {
      "id": "9VEz8DyZ4fcOa4v2sAj0bf34Bns2",
      "own": 31,
      "picked": 19,
      "recorded": 0,
      "wishlist": 0
    },
    {
      "id": "NIq4FDSVbgQEdiKW4t3bmcby6Zn2",
      "own": 30,
      "picked": 16,
      "recorded": 16,
      "wishlist": 19
    },
    {
      "id": "0oQdsctEO8ZF3V4qPz8QhGAc7qM2",
      "own": 28,
      "picked": 16,
      "recorded": 14,
      "wishlist": 0
    },
    {
      "id": "AAxvDXH5dmetjYcQkkUv0HewD903",
      "own": 28,
      "picked": 10,
      "recorded": 2,
      "wishlist": 14
    },
    {
      "id": "zDpOLv3IAPSdIwPpSPGf8cKQumx2",
      "own": 28,
      "picked": 8,
      "recorded": 8,
      "wishlist": 0
    },
    {
      "id": "MVapW0c6QKXnl7ZziTdVCRl1OrV2",
      "own": 26,
      "picked": 7,
      "recorded": 4,
      "wishlist": 0
    },
    {
      "id": "tMviHgaeoqWKbYNrafjpMyJT1rh2",
      "displayName": "minkle",
      "own": 26,
      "picked": 24,
      "recorded": 8,
      "wishlist": 3
    },
    {
      "id": "pecmaqensaUa6zWaoebKd7SGvTE3",
      "own": 25,
      "picked": 16,
      "recorded": 12,
      "wishlist": 0
    },
    {
      "id": "80bURznx33NMnjVJaJANQHWHTml1",
      "own": 23,
      "picked": 24,
      "recorded": 3,
      "wishlist": 0
    },
    {
      "id": "semFxBW0MVMRzYSsCRmxRNEJy582",
      "own": 23,
      "picked": 19,
      "recorded": 0,
      "wishlist": 0
    },
    {
      "id": "UCvM8BKJ71NkbMzip7LTSOJhf5s1",
      "own": 22,
      "picked": 6,
      "recorded": 5,
      "wishlist": 0
    },
    {
      "id": "XASYb4rzsbXadVCPdrUJYTkYw8x2",
      "own": 9,
      "picked": 15,
      "recorded": 8,
      "wishlist": 0
    },
    {
      "id": "1hGLFP199GUD0ywbyW25WwJs0Zt1",
      "own": 20,
      "picked": 12,
      "recorded": 0,
      "wishlist": 2
    },
    {
      "id": "iAAvnabspDRtL9W0Mo6Iob7I2mc2",
      "own": 20,
      "picked": 9,
      "recorded": 1,
      "wishlist": 18
    },
    {
      "id": "JZ4xWkMjpSMQUOHMH31zUQWI75c2",
      "own": 20,
      "picked": 3,
      "recorded": 2,
      "wishlist": 0
    },
    {
      "id": "SHT62Cs3JLSGDOKwzOxCLYyYpor1",
      "own": 19,
      "picked": 16,
      "recorded": 3,
      "wishlist": 0
    },
    {
      "id": "L4slGjIPoXhlW8u8METvt6nJSgs2",
      "own": 18,
      "picked": 12,
      "recorded": 0,
      "wishlist": 0
    },
    {
      "id": "E2C8Z9u2IFREIqEmqccifBEj1XZ2",
      "own": 17,
      "picked": 8,
      "recorded": 4,
      "wishlist": 0
    },
    {
      "id": "NgYkzFJvlWTs5UdyjK40MfJodxc2",
      "own": 9,
      "picked": 11,
      "recorded": 0,
      "wishlist": 8
    },
    {
      "id": "Q9u8BMKkg2axTm0sSpBUGZSQYgL2",
      "own": 15,
      "picked": 14,
      "recorded": 4,
      "wishlist": 41
    },
    {
      "id": "6fP71xwAg8fNzx2jwArw99Mx7ft2",
      "own": 16,
      "picked": 10,
      "recorded": 0,
      "wishlist": 0
    },
    {
      "id": "bXjsrWBrktUICpvCGsbaXRyGXNh1",
      "own": 16,
      "picked": 11,
      "recorded": 8,
      "wishlist": 5
    },
    {
      "id": "GYxNI0MazBgvziJ0fcPsNzYb2063",
      "own": 15,
      "picked": 11,
      "recorded": 11,
      "wishlist": 0
    },
    {
      "id": "T8b2eW3US8MHiFOqhzGBuvueVQw1",
      "own": 16,
      "picked": 6,
      "recorded": 0,
      "wishlist": 1
    },
    {
      "id": "1dlgPlIKx1dmCO3SH8axvWDbqZB2",
      "displayName": "McFierce",
      "own": 15,
      "picked": 11,
      "recorded": 9,
      "wishlist": 0
    },
    {
      "id": "3o6Sjf3YsUTEdqupTsRT9S3m6tN2",
      "own": 14,
      "picked": 10,
      "recorded": 1,
      "wishlist": 7
    },
    {
      "id": "gikUMfGW1SbM7EL0vzxQZF9yuOm2",
      "own": 15,
      "picked": 7,
      "recorded": 0,
      "wishlist": 0
    },
    {
      "id": "gL7S6Qpf7bRGkrBjLFwMKUOhGQ52",
      "own": 15,
      "picked": 9,
      "recorded": 0,
      "wishlist": 19
    },
    {
      "id": "Lr2BW4umY4WVcdVGKfNqzb863PM2",
      "own": 14,
      "picked": 14,
      "recorded": 0,
      "wishlist": 0
    },
    {
      "id": "TSCqgOfBewZqOmTEyxrAAn2m6xC2",
      "own": 15,
      "picked": 14,
      "recorded": 10,
      "wishlist": 0
    },
    {
      "id": "3YuT1axkjzgJJ9xrkfmV4crDEMm2",
      "own": 14,
      "picked": 8,
      "recorded": 0,
      "wishlist": 11
    },
    {
      "id": "tmS1NuRSBFhzPgPjEFRFzdNXcAG3",
      "own": 14,
      "picked": 7,
      "recorded": 1,
      "wishlist": 2
    },
    {
      "id": "YbYpWFTXMiZ7v2D60MONxxviOPN2",
      "own": 12,
      "picked": 7,
      "recorded": 2,
      "wishlist": 0
    },
    {
      "id": "wGsZIqrDwTPxBpeaQeXT7xFFj2m2",
      "own": 8,
      "picked": 13,
      "recorded": 0,
      "wishlist": 0
    },
    {
      "id": "0RLaiDlZEgNlhip0flwwhqHSRZy2",
      "own": 12,
      "picked": 12,
      "recorded": 0,
      "wishlist": 2
    },
    {
      "id": "5Ac77p91YpP853OEujcYpi84y6C3",
      "own": 12,
      "picked": 12,
      "recorded": 4,
      "wishlist": 0
    },
    {
      "id": "etXEek6CwjX64ZRmKHRm7lccbTS2",
      "own": 12,
      "picked": 12,
      "recorded": 0,
      "wishlist": 3
    },
    {
      "id": "GglRA219SOULG0gK7rnlIhkL85Q2",
      "own": 11,
      "picked": 6,
      "recorded": 4,
      "wishlist": 4
    },
    {
      "id": "s4pkkRIJa9X2xpNsQv8PDQl043D2",
      "own": 12,
      "picked": 8,
      "recorded": 0,
      "wishlist": 3
    },
    {
      "id": "tgmzqmlx1ablsG0OOEF6WYTet3y2",
      "own": 12,
      "picked": 10,
      "recorded": 3,
      "wishlist": 0
    },
    {
      "id": "9ZnATH1b3pe0vzgEjzq0d0Uskcf1",
      "own": 11,
      "picked": 8,
      "recorded": 1,
      "wishlist": 0
    },
    {
      "id": "fy20hz7u90hB0gbfcO3k9h7hmk52",
      "own": 1,
      "picked": 11,
      "recorded": 0,
      "wishlist": 1
    },
    {
      "id": "gHep3KnMHjVYU8qUpkV1CLjxy3s2",
      "own": 11,
      "picked": 9,
      "recorded": 2,
      "wishlist": 0
    },
    {
      "id": "mzhcU8EDkhX9N8KT1k4sHJ1Zuho2",
      "own": 11,
      "picked": 4,
      "recorded": 2,
      "wishlist": 0
    },
    {
      "id": "oi1MPhSKQ6U5HnzWXjwH3xUCsd33",
      "own": 11,
      "picked": 7,
      "recorded": 0,
      "wishlist": 0
    },
    {
      "id": "pa0Fe38BgdV9fcL5PPNToNd7NVU2",
      "own": 8,
      "picked": 8,
      "recorded": 2,
      "wishlist": 1
    },
    {
      "id": "T5oiFTrhbDOQWyHqcwEG8ySVXVK2",
      "own": 11,
      "picked": 9,
      "recorded": 0,
      "wishlist": 0
    },
    {
      "id": "UyxIZzLTPEPT6IN6ShvfHJrOSFq2",
      "own": 11,
      "picked": 7,
      "recorded": 1,
      "wishlist": 0
    },
    {
      "id": "fNwihzEBzKPjgttQDxkDmdejifh1",
      "own": 10,
      "picked": 6,
      "recorded": 0,
      "wishlist": 0
    },
    {
      "id": "KMiSr8NsJPeVvEM6qRF6iJkUwyk1",
      "own": 10,
      "picked": 3,
      "recorded": 3,
      "wishlist": 5
    },
    {
      "id": "lQ7mDeWar0VCFoB1FPzH3gxul143",
      "own": 10,
      "picked": 6,
      "recorded": 0,
      "wishlist": 2
    },
    {
      "id": "p4pEjIXaGJamgCgd834N9V8oj2R2",
      "own": 10,
      "picked": 8,
      "recorded": 0,
      "wishlist": 0
    },
    {
      "id": "VsrJrQC3Jqc5WPRRrVHPJ0FGn6h2",
      "own": 10,
      "picked": 6,
      "recorded": 5,
      "wishlist": 0
    },
    {
      "id": "YYqP720JjRMid50Hl6TcgJdY7Vn2",
      "own": 10,
      "picked": 9,
      "recorded": 0,
      "wishlist": 0
    },
    {
      "id": "ZchaUvEsBkcFfDVqvEn5r5wfhYj1",
      "own": 10,
      "picked": 5,
      "recorded": 3,
      "wishlist": 1
    },
    {
      "id": "20lUl6bI4OTnC2RpuowvRtgdlCb2",
      "own": 9,
      "picked": 5,
      "recorded": 3,
      "wishlist": 0
    },
    {
      "id": "3wZdjXs2JlduwzQqmFPcxpsZMTO2",
      "own": 9,
      "picked": 5,
      "recorded": 0,
      "wishlist": 0
    },
    {
      "id": "9oY70Km7xMgPX6WZAk05XOZ7NYV2",
      "own": 8,
      "picked": 6,
      "recorded": 0,
      "wishlist": 18
    },
    {
      "id": "JQcjin5vm0Ms8hVaMj1uGUmUDYl2",
      "own": 9,
      "picked": 6,
      "recorded": 0,
      "wishlist": 0
    },
    {
      "id": "qbhlMiotXNWU5GNXEBkYr8NqyW82",
      "own": 9,
      "picked": 6,
      "recorded": 0,
      "wishlist": 0
    },
    {
      "id": "tMVuRnJYwtO1AORMm9L36JM3urt1",
      "own": 9,
      "picked": 6,
      "recorded": 0,
      "wishlist": 1
    },
    {
      "id": "UXrem7pXmAhyxstHNBgvkfVKYKn2",
      "own": 8,
      "picked": 6,
      "recorded": 0,
      "wishlist": 0
    },
    {
      "id": "VoICvV7xjuVSMAl5woaAfW5N0rE2",
      "own": 6,
      "picked": 3,
      "recorded": 0,
      "wishlist": 5
    },
    {
      "id": "VytylrsofvcA5wIeDMD8Ex3ToNu1",
      "own": 9,
      "picked": 9,
      "recorded": 0,
      "wishlist": 0
    },
    {
      "id": "zecYoVJ3HSd3TPUjzlrZWFBkwkJ3",
      "own": 9,
      "picked": 4,
      "recorded": 1,
      "wishlist": 0
    },
    {
      "id": "67F68Oo3ZHMptjUUw2DTIAQS54Q2",
      "own": 8,
      "picked": 4,
      "recorded": 1,
      "wishlist": 0
    },
    {
      "id": "aFkfNlrHUMNfGLxciGnHkPvePvd2",
      "own": 8,
      "picked": 4,
      "recorded": 0,
      "wishlist": 0
    },
    {
      "id": "DbonQd8KejYweTbGR3frCgmYVot2",
      "own": 8,
      "picked": 3,
      "recorded": 0,
      "wishlist": 0
    },
    {
      "id": "e1KAjx5UHjSobdu8rqE2uXPYS6G2",
      "own": 8,
      "picked": 8,
      "recorded": 3,
      "wishlist": 0
    },
    {
      "id": "FI44CC9pfYVl4y7UXwNCNmTBUP02",
      "own": 8,
      "picked": 5,
      "recorded": 0,
      "wishlist": 0
    },
    {
      "id": "MfyFIBmefYdC19NVZ6EnuDDxbb32",
      "own": 8,
      "picked": 5,
      "recorded": 0,
      "wishlist": 0
    },
    {
      "id": "MRJkKsdSBEgPBHNdooncApTlP533",
      "own": 8,
      "picked": 6,
      "recorded": 0,
      "wishlist": 0
    },
    {
      "id": "rrKEMiNLqORLE38NyhCOcGY3SQ33",
      "own": 8,
      "picked": 6,
      "recorded": 1,
      "wishlist": 0
    },
    {
      "id": "SeGFupBfp1dkwSvySCByKPff6Y23",
      "own": 8,
      "picked": 8,
      "recorded": 2,
      "wishlist": 0
    },
    {
      "id": "sg2brfk1aPOcl0XBVHtdi71omxu1",
      "own": 8,
      "picked": 3,
      "recorded": 0,
      "wishlist": 0
    },
    {
      "id": "SY1SBt51fSayKd0O4Wkf8z9gkMi2",
      "own": 8,
      "picked": 8,
      "recorded": 0,
      "wishlist": 0
    },
    {
      "id": "TxvOS8wlefaYlUpFakbGEhzgcOJ3",
      "own": 8,
      "picked": 3,
      "recorded": 2,
      "wishlist": 0
    },
    {
      "id": "vOi8rfTRluYlcVizuVvX9PWFJdn2",
      "own": 8,
      "picked": 6,
      "recorded": 0,
      "wishlist": 0
    },
    {
      "id": "Yviw9tavT4bHb5YjjpHd8PrWvQa2",
      "own": 8,
      "picked": 3,
      "recorded": 0,
      "wishlist": 7
    },
    {
      "id": "EFtwbQuNhFhr0HgDG0PAnuc9HNh1",
      "own": 7,
      "picked": 4,
      "recorded": 1,
      "wishlist": 0
    },
    {
      "id": "i4TVsJXYUCRXHrWaxJoyga9M50u2",
      "own": 0,
      "picked": 7,
      "recorded": 0,
      "wishlist": 0
    },
    {
      "id": "KodM49URHhO9RDy1bA4v3pnJxLo1",
      "own": 7,
      "picked": 2,
      "recorded": 0,
      "wishlist": 0
    },
    {
      "id": "PErOj3bjUecOjCGSvkFHgCC8IT02",
      "own": 7,
      "picked": 2,
      "recorded": 0,
      "wishlist": 0
    },
    {
      "id": "sr28fiHskOPFYqIDlUerUyQ2QmZ2",
      "own": 7,
      "picked": 4,
      "recorded": 0,
      "wishlist": 0
    },
    {
      "id": "U4igcnwrxvOqbUH7sYQ8ycmq5Un2",
      "own": 6,
      "picked": 6,
      "recorded": 0,
      "wishlist": 0
    },
    {
      "id": "wCDT1geYXfUhxguyoCe2pcl3Ae22",
      "own": 0,
      "picked": 7,
      "recorded": 0,
      "wishlist": 0
    },
    {
      "id": "ZShiTe5M6ycFdZlZGomkImU5fU72",
      "own": 7,
      "picked": 5,
      "recorded": 0,
      "wishlist": 0
    },
    {
      "id": "aDK40fFpHOQV1HRxI4onn9CpGbE3",
      "own": 6,
      "picked": 3,
      "recorded": 0,
      "wishlist": 3
    },
    {
      "id": "bGfZ4f3nxmaKdiQT5nAaWDxDGcK2",
      "own": 6,
      "picked": 6,
      "recorded": 0,
      "wishlist": 0
    },
    {
      "id": "sbCGVh9CEmUfcZCo96i3DLMlAw02",
      "own": 6,
      "picked": 4,
      "recorded": 0,
      "wishlist": 0
    },
    {
      "id": "yKWk4Q5mOFY6zYgE2bEOa68LA3y2",
      "own": 6,
      "picked": 5,
      "recorded": 0,
      "wishlist": 0
    },
    {
      "id": "66IPmGPbuEcn4lxWslW1uxZCdWF2",
      "own": 5,
      "picked": 5,
      "recorded": 0,
      "wishlist": 0
    },
    {
      "id": "67VxrPydWTeHHthsIbjJsBDEoff1",
      "own": 5,
      "picked": 3,
      "recorded": 2,
      "wishlist": 7
    },
    {
      "id": "90dBh8wPevWq9op6UiQURRK5WXf2",
      "own": 5,
      "picked": 4,
      "recorded": 0,
      "wishlist": 0
    },
    {
      "id": "aBweXDLnKeODAPFp2y4m2CSLCkN2",
      "own": 5,
      "picked": 3,
      "recorded": 0,
      "wishlist": 0
    },
    {
      "id": "B7RW37i2KXWkj5bn5YvH5LXGm5T2",
      "own": 5,
      "picked": 3,
      "recorded": 0,
      "wishlist": 3
    },
    {
      "id": "dZgqF7Yln7dNDxhJCn2NJ6q546E2",
      "own": 5,
      "picked": 3,
      "recorded": 0,
      "wishlist": 0
    },
    {
      "id": "eKkOC4lRCvQdO8QgImGIZnwjVPM2",
      "own": 5,
      "picked": 2,
      "recorded": 0,
      "wishlist": 0
    },
    {
      "id": "FlcpRoZBWQbzkpiGnVc6GY7zk4B2",
      "own": 5,
      "picked": 5,
      "recorded": 3,
      "wishlist": 0
    },
    {
      "id": "kvFqeAtcWQPvXGibHuKzHfZKCed2",
      "own": 5,
      "picked": 2,
      "recorded": 0,
      "wishlist": 1
    },
    {
      "id": "m4lQBx5ivDbMHvzO1NRxs5m4Y3K2",
      "own": 2,
      "picked": 3,
      "recorded": 0,
      "wishlist": 0
    },
    {
      "id": "oRThO9GP10V1Tiz9FKIm6iPlMnw2",
      "own": 5,
      "picked": 4,
      "recorded": 0,
      "wishlist": 2
    },
    {
      "id": "qzWsUKXGxKZ0FUUE43Gc570TApx1",
      "own": 5,
      "picked": 3,
      "recorded": 0,
      "wishlist": 0
    },
    {
      "id": "W4vfwHlF0EVD8s9OMR72r1ANU7g1",
      "own": 4,
      "picked": 5,
      "recorded": 2,
      "wishlist": 2
    },
    {
      "id": "WVYyeM8C0mgEWV2pzARsUlo7WiM2",
      "own": 5,
      "picked": 2,
      "recorded": 0,
      "wishlist": 0
    },
    {
      "id": "XyzL4lHI4oW3s2on4F0FS2Otccv2",
      "own": 5,
      "picked": 4,
      "recorded": 0,
      "wishlist": 1
    },
    {
      "id": "6dwSEPg4ohUaS35sHQxrFLdrQf12",
      "own": 4,
      "picked": 3,
      "recorded": 1,
      "wishlist": 0
    },
    {
      "id": "aCgtTYJIJTWZ1wgg2VDYMfObybH3",
      "own": 4,
      "picked": 4,
      "recorded": 3,
      "wishlist": 0
    },
    {
      "id": "AKTTxuCwMeReoCuxOsurCHvBDtd2",
      "own": 4,
      "picked": 2,
      "recorded": 0,
      "wishlist": 0
    },
    {
      "id": "Ao9Z6mwLQCPuTemsixXktl8Q03I2",
      "own": 4,
      "picked": 1,
      "recorded": 0,
      "wishlist": 0
    },
    {
      "id": "DVr6WAdLSnZUCVYbFO2tHNYWnVE2",
      "own": 4,
      "picked": 3,
      "recorded": 3,
      "wishlist": 0
    },
    {
      "id": "EcvPD1gAKIZtz4JsPP0sYAfhQ823",
      "own": 4,
      "picked": 0,
      "recorded": 0,
      "wishlist": 1
    },
    {
      "id": "ERZblRCp8TO5OxqDRKiyAvfN9tI2",
      "own": 4,
      "picked": 4,
      "recorded": 1,
      "wishlist": 0
    },
    {
      "id": "gc787Kqo05YRiW96jQBWRGivcQR2",
      "own": 3,
      "picked": 4,
      "recorded": 0,
      "wishlist": 0
    },
    {
      "id": "ggZRr21hMaSnTiPF6qZFcbBilvF2",
      "own": 4,
      "picked": 4,
      "recorded": 0,
      "wishlist": 1
    },
    {
      "id": "JZUFtKmmzset70z6XRgbOeReAJQ2",
      "own": 4,
      "picked": 2,
      "recorded": 0,
      "wishlist": 0
    },
    {
      "id": "Ls8cmC4MGdbwyS1DRjvuSY5SyuJ3",
      "own": 4,
      "picked": 3,
      "recorded": 3,
      "wishlist": 0
    },
    {
      "id": "mgMcYfbOKzUttNEzg8lKqOZLP5B2",
      "own": 4,
      "picked": 4,
      "recorded": 1,
      "wishlist": 0
    },
    {
      "id": "NjoS78rFv7OURceuG5hP3IfkBEA2",
      "own": 2,
      "picked": 4,
      "recorded": 0,
      "wishlist": 0
    },
    {
      "id": "Nse5boBJ72VOuwOZ9cgB2XvLfIx1",
      "own": 4,
      "picked": 2,
      "recorded": 0,
      "wishlist": 0
    },
    {
      "id": "u2ojqqF2MeWm6cx6cERa9zdqqGP2",
      "own": 4,
      "picked": 2,
      "recorded": 0,
      "wishlist": 5
    },
    {
      "id": "udUsrkg5xRhsvtezXvwguknOaZO2",
      "own": 4,
      "picked": 3,
      "recorded": 0,
      "wishlist": 0
    },
    {
      "id": "vtHdxJ5n7uMpE7Gx97eHbYuQiBO2",
      "own": 3,
      "picked": 4,
      "recorded": 0,
      "wishlist": 0
    },
    {
      "id": "WrsHTOQqIpTRQZOYA2NelLJzZdM2",
      "own": 4,
      "picked": 3,
      "recorded": 0,
      "wishlist": 0
    },
    {
      "id": "WYovftS7LPRIqoimIrfuua7p7nJ3",
      "own": 1,
      "picked": 3,
      "recorded": 2,
      "wishlist": 0
    },
    {
      "id": "yWwm05f4zpdB4cH5NFACNRL3OCj1",
      "own": 4,
      "picked": 4,
      "recorded": 0,
      "wishlist": 0
    },
    {
      "id": "ZPxxR58qsRVZXAvaHFM9VzO2isH2",
      "own": 4,
      "picked": 4,
      "recorded": 0,
      "wishlist": 0
    },
    {
      "id": "1YxRQLjpPjegrWwSeXtWsCpcGgq1",
      "own": 1,
      "picked": 2,
      "recorded": 0,
      "wishlist": 0
    },
    {
      "id": "3cswFxn0cUOkveqnGaTuNZthKiG2",
      "own": 3,
      "picked": 2,
      "recorded": 0,
      "wishlist": 0
    },
    {
      "id": "6jTACFnnvOgSZJWzS5frk9HQpjP2",
      "own": 3,
      "picked": 3,
      "recorded": 0,
      "wishlist": 2
    },
    {
      "id": "a55EC0MNJQVTDGDffgeTIKWHbws2",
      "own": 3,
      "picked": 3,
      "recorded": 2,
      "wishlist": 4
    },
    {
      "id": "BnILHfxHm1S8BS3Nj4jeFTC9cdf2",
      "own": 4,
      "picked": 0,
      "recorded": 0,
      "wishlist": 2
    },
    {
      "id": "EgB8TQirrLVJSmMVtZrjCIPYxxq1",
      "own": 0,
      "picked": 3,
      "recorded": 3,
      "wishlist": 0
    },
    {
      "id": "fWnJfzxsqwgfzjgEAbFzyVXFbC83",
      "own": 3,
      "picked": 0,
      "recorded": 0,
      "wishlist": 6
    },
    {
      "id": "gdozgtCZtRUM9vM3yU4XGlgwZoi1",
      "own": 3,
      "picked": 2,
      "recorded": 0,
      "wishlist": 0
    },
    {
      "id": "gfc8zXRj1wMWBe4QGKpmGJdqw5v2",
      "own": 3,
      "picked": 2,
      "recorded": 0,
      "wishlist": 0
    },
    {
      "id": "jVMz7k9QgKXgCcAZQ09FLq0zv7s2",
      "own": 3,
      "picked": 1,
      "recorded": 0,
      "wishlist": 0
    },
    {
      "id": "nu4dxbLJLUbvWpNlomTFL0lm0E03",
      "own": 3,
      "picked": 2,
      "recorded": 0,
      "wishlist": 2
    },
    {
      "id": "ozoJyQki3ySRHi2NJvZMkuNIT913",
      "own": 3,
      "picked": 3,
      "recorded": 0,
      "wishlist": 0
    },
    {
      "id": "Ph5iuspAlsVmuUiOTUn8TJLAC0c2",
      "own": 3,
      "picked": 3,
      "recorded": 0,
      "wishlist": 0
    },
    {
      "id": "uLbd5ZwwbHNQ5CaRV7WkN2ZSBH73",
      "own": 7,
      "picked": 2,
      "recorded": 0,
      "wishlist": 11
    },
    {
      "id": "VCw80rjsGzVHvD9v5OTzJ662ni62",
      "own": 3,
      "picked": 2,
      "recorded": 2,
      "wishlist": 2
    },
    {
      "id": "VPTSnjxUXwOs8uusWDIAvXsKtJo2",
      "own": 3,
      "picked": 3,
      "recorded": 2,
      "wishlist": 0
    },
    {
      "id": "y5acMzkHgYR3jNCkjpWxa9Ul6Rw1",
      "own": 2,
      "picked": 2,
      "recorded": 2,
      "wishlist": 0
    },
    {
      "id": "yMtI9gABttZLrRGHP5y6mAHDHWn2",
      "own": 3,
      "picked": 2,
      "recorded": 0,
      "wishlist": 0
    },
    {
      "id": "YrUALb34vQZEF0jbcE6abtQelvw1",
      "own": 3,
      "picked": 3,
      "recorded": 0,
      "wishlist": 0
    },
    {
      "id": "1VCBwbDaV3MLa8J7FZZkaGVsz0p1",
      "own": 2,
      "picked": 2,
      "recorded": 0,
      "wishlist": 0
    },
    {
      "id": "3cf9v3uykYYLcSMyi5pdH9lxCOH3",
      "own": 1,
      "picked": 2,
      "recorded": 0,
      "wishlist": 0
    },
    {
      "id": "4xH2Fk1eudT8CxyAfIme71USSV72",
      "own": 2,
      "picked": 1,
      "recorded": 0,
      "wishlist": 0
    },
    {
      "id": "A7MNzg6jrNUIgfEkk8U0JzZndcx2",
      "own": 2,
      "picked": 1,
      "recorded": 0,
      "wishlist": 1
    },
    {
      "id": "aIGKIpRUCMO75wzDbX8dZyByW7U2",
      "own": 2,
      "picked": 1,
      "recorded": 0,
      "wishlist": 7
    },
    {
      "id": "b86xPsfPnIPE9hDNuMUMEBPjTQ42",
      "own": 2,
      "picked": 1,
      "recorded": 0,
      "wishlist": 5
    },
    {
      "id": "BjmJzJTpVWUvCvDoKytlToKcU2r2",
      "own": 2,
      "picked": 1,
      "recorded": 0,
      "wishlist": 0
    },
    {
      "id": "bSlUdd7L5nVWwU15bJKhgrsjE7v1",
      "own": 2,
      "picked": 0,
      "recorded": 0,
      "wishlist": 0
    },
    {
      "id": "By5bHfbdv1cxDtoUDFOGTy1FBoX2",
      "own": 2,
      "picked": 2,
      "recorded": 0,
      "wishlist": 0
    },
    {
      "id": "C7lHNyuO2xbFSwueIfdjmQLHgFv1",
      "own": 2,
      "picked": 2,
      "recorded": 0,
      "wishlist": 4
    },
    {
      "id": "CBR6g2vETpM81EIjDLbyHKJk36Z2",
      "own": 2,
      "picked": 2,
      "recorded": 0,
      "wishlist": 3
    },
    {
      "id": "dBZGruLcEQXKa1tYLWrkEw0ybKq1",
      "own": 2,
      "picked": 1,
      "recorded": 0,
      "wishlist": 0
    },
    {
      "id": "ESYZvKM2hxU75MJcAUuG40vKbsm2",
      "own": 2,
      "picked": 1,
      "recorded": 0,
      "wishlist": 0
    },
    {
      "id": "fsFBM3GGYObyeDPhOEfEKhjGGQE2",
      "own": 2,
      "picked": 2,
      "recorded": 0,
      "wishlist": 0
    },
    {
      "id": "JJnsupQNtBbtoB3PyUQ4nQEvGo92",
      "own": 2,
      "picked": 2,
      "recorded": 0,
      "wishlist": 0
    },
    {
      "id": "La9pLfwlesOa9fvRrI2FfmgPOxI3",
      "own": 2,
      "picked": 1,
      "recorded": 0,
      "wishlist": 0
    },
    {
      "id": "mGEw1QxsjDYjnbcnUPMI5bIoeE02",
      "own": 2,
      "picked": 2,
      "recorded": 0,
      "wishlist": 0
    },
    {
      "id": "MGqDoM7vmtRHQictJfRfu9S2TtI2",
      "own": 2,
      "picked": 1,
      "recorded": 0,
      "wishlist": 0
    },
    {
      "id": "pIz6OGcSqrelSmGiZhnjDpKnkeq2",
      "own": 2,
      "picked": 2,
      "recorded": 2,
      "wishlist": 0
    },
    {
      "id": "PwCiYNAOa6TWLvmwjG6Ne07vDlq2",
      "own": 0,
      "picked": 2,
      "recorded": 0,
      "wishlist": 0
    },
    {
      "id": "skDlU7iZ4PRMCRlQBvhLxWP2t1D2",
      "own": 2,
      "picked": 2,
      "recorded": 1,
      "wishlist": 0
    },
    {
      "id": "tXYeBs5AY1gen7aY1JZBL74TrDF2",
      "own": 2,
      "picked": 2,
      "recorded": 0,
      "wishlist": 0
    },
    {
      "id": "uBoi9XYuYAOY2Sv5xB9Nb7BUPAd2",
      "own": 2,
      "picked": 0,
      "recorded": 0,
      "wishlist": 0
    },
    {
      "id": "uXB1uzkAl5SosUGDzaIT46JMOxp2",
      "own": 2,
      "picked": 2,
      "recorded": 0,
      "wishlist": 0
    },
    {
      "id": "Vc0G7kyPkWM52sT46tW5bw9xGbv2",
      "own": 2,
      "picked": 0,
      "recorded": 0,
      "wishlist": 0
    },
    {
      "id": "vWw4mxzI5VPBOVKIa4CEQNu9ZE93",
      "own": 1,
      "picked": 2,
      "recorded": 0,
      "wishlist": 0
    },
    {
      "id": "XiXHpSKnhlRJXBwZ94ZCwfOIRnD2",
      "own": 2,
      "picked": 2,
      "recorded": 0,
      "wishlist": 0
    },
    {
      "id": "xjjQ8mMPJqPY6IhojU3yzQDJtWk1",
      "own": 2,
      "picked": 2,
      "recorded": 2,
      "wishlist": 0
    },
    {
      "id": "xmD1FIoUyNRx50YMDhvnXpz5XtC3",
      "own": 2,
      "picked": 2,
      "recorded": 0,
      "wishlist": 0
    },
    {
      "id": "YXZY1ExTLwOwKhdy50JbVN5yT8Z2",
      "own": 2,
      "picked": 2,
      "recorded": 1,
      "wishlist": 0
    },
    {
      "id": "0TFmibjz4Id4YQwfDnbdXNRdv413",
      "own": 1,
      "picked": 0,
      "recorded": 0,
      "wishlist": 0
    },
    {
      "id": "0YgLtYhMQRhFn7byFz81R0obeqb2",
      "own": 1,
      "picked": 1,
      "recorded": 1,
      "wishlist": 0
    },
    {
      "id": "1pZGeK4xlqRJpiqfi0xsTfkycLR2",
      "own": 1,
      "picked": 0,
      "recorded": 0,
      "wishlist": 0
    },
    {
      "id": "3ci7SzO9SWfgBcHUGXzT4YJMcrj2",
      "own": 1,
      "picked": 1,
      "recorded": 0,
      "wishlist": 0
    },
    {
      "id": "3fnAHyK4eNTaUCHW3fE0RDBwbFp1",
      "own": 1,
      "picked": 0,
      "recorded": 0,
      "wishlist": 0
    },
    {
      "id": "4eaIe3Gna9QelgVZbKZHs41zIiB2",
      "own": 1,
      "picked": 1,
      "recorded": 0,
      "wishlist": 0
    },
    {
      "id": "5HH7tKiVlyf8aG3Kixs8P03KUwZ2",
      "own": 1,
      "picked": 1,
      "recorded": 0,
      "wishlist": 0
    },
    {
      "id": "60xbEDcTSBYQHYnOeTHbYctToL22",
      "own": 1,
      "picked": 0,
      "recorded": 0,
      "wishlist": 0
    },
    {
      "id": "6YP23fxALQQD4EyXZqyhPMLN4IC3",
      "own": 1,
      "picked": 1,
      "recorded": 0,
      "wishlist": 1
    },
    {
      "id": "7eMRRE06naM3lzct4HYV1rxj0VJ2",
      "own": 1,
      "picked": 1,
      "recorded": 0,
      "wishlist": 2
    },
    {
      "id": "cKDcN4l9eJM6XwqYPsf5lVVEe2J3",
      "own": 1,
      "picked": 1,
      "recorded": 0,
      "wishlist": 0
    },
    {
      "id": "CN98UYTUmGM45yTfPK1Ztmf0ez83",
      "own": 1,
      "picked": 1,
      "recorded": 0,
      "wishlist": 0
    },
    {
      "id": "e7lny5XiD2QLqWDnUN76rzJP3gk1",
      "own": 1,
      "picked": 0,
      "recorded": 0,
      "wishlist": 0
    },
    {
      "id": "eDyBNVT8ajPheuXuThQxPTIP52t1",
      "own": 1,
      "picked": 1,
      "recorded": 1,
      "wishlist": 0
    },
    {
      "id": "EW5WegpzHHSDfwezt0BO3eQSbuC2",
      "own": 1,
      "picked": 1,
      "recorded": 0,
      "wishlist": 0
    },
    {
      "id": "G5ubbgA6HkOHFiEkDvZmL79zfqW2",
      "own": 1,
      "picked": 1,
      "recorded": 0,
      "wishlist": 0
    },
    {
      "id": "Gg9KxwHOwBf03QAIdOgZbfW3hRo1",
      "own": 1,
      "picked": 1,
      "recorded": 1,
      "wishlist": 0
    },
    {
      "id": "ihicFrsL7qa3g67PhaYcCoeuaW02",
      "own": 1,
      "picked": 1,
      "recorded": 0,
      "wishlist": 0
    },
    {
      "id": "kAOKXqmpo7Nhcrq5OBpYarFeJb53",
      "own": 1,
      "picked": 0,
      "recorded": 0,
      "wishlist": 0
    },
    {
      "id": "L1wxn4E9FANnOzELuv9IMc5ghyR2",
      "own": 1,
      "picked": 0,
      "recorded": 0,
      "wishlist": 0
    },
    {
      "id": "N58nvsgcPlMV48yceKvCMXj4X602",
      "own": 1,
      "picked": 1,
      "recorded": 1,
      "wishlist": 0
    },
    {
      "id": "NE73020hwGbmEXE91kNULPVcdnD2",
      "own": 1,
      "picked": 1,
      "recorded": 0,
      "wishlist": 2
    },
    {
      "id": "nQ7f5B1H2IbPY6Hqvxebxl1jEXu2",
      "own": 0,
      "picked": 1,
      "recorded": 1,
      "wishlist": 1
    },
    {
      "id": "OAq4yIdv1bRSUQK6l2KUru57cjy1",
      "own": 1,
      "picked": 1,
      "recorded": 0,
      "wishlist": 0
    },
    {
      "id": "PKLCjuizbwgC2lV4pV06OQk4VM73",
      "own": 1,
      "picked": 1,
      "recorded": 0,
      "wishlist": 0
    },
    {
      "id": "S86oRKKpLOXeh785pzz0gMPb7Jf2",
      "own": 1,
      "picked": 1,
      "recorded": 1,
      "wishlist": 0
    },
    {
      "id": "tX09wNUl96MyNWanMwow1Q1PsAg2",
      "own": 1,
      "picked": 0,
      "recorded": 0,
      "wishlist": 0
    },
    {
      "id": "w01mnAZrI8eupJw9vPe9FR06g582",
      "own": 1,
      "picked": 1,
      "recorded": 0,
      "wishlist": 0
    },
    {
      "id": "xaF8QP5qCma1TAMxQZou1IfTSle2",
      "own": 1,
      "picked": 1,
      "recorded": 0,
      "wishlist": 0
    }
  ],
  "metadata": {
    "updatedDateTime": "2023-12-19T14:21:45"
  }
}
